exastolog/InitialState.py
exastolog/Model.py
exastolog/Simulation.py
exastolog/Solution.py
exastolog/StateTransitionGraph.py
exastolog/StateTransitionSubGraphs.py
exastolog/StateTransitionTable.py
exastolog/TransRateTable.py
exastolog/__init__.py
exastolog-1.0.0a5.dist-info/LICENSE
exastolog-1.0.0a5.dist-info/METADATA
exastolog-1.0.0a5.dist-info/WHEEL
exastolog-1.0.0a5.dist-info/top_level.txt
exastolog-1.0.0a5.dist-info/RECORD
